{
  "metadata": {
    "source": "gktoday.in",
    "category_slug": "current-affairs-quiz-march-2021",
    "title": "Current Affairs Quiz - March, 2021",
    "page": 1,
    "total_pages": 5,
    "generated_at": "2026-05-02 05:47:29",
    "total_questions": 10,
    "scraped_at": "2026-05-02 11:58:25"
  },
  "questions": [
    {
      "id": 1,
      "question": "Which is the world’s first country to ban all Vulture-Toxic Drugs known so far?",
      "options": [
        {
          "label": "A",
          "text": "India"
        },
        {
          "label": "B",
          "text": "Bangladesh"
        },
        {
          "label": "C",
          "text": "Russia"
        },
        {
          "label": "D",
          "text": "New Zealand"
        }
      ],
      "answer": {
        "label": "B",
        "text": "Bangladesh"
      },
      "explanation": "Bangladesh has recently banned the painkiller ketoprofen used widely to treat the cattle. With this it became the first country to ban all the drugs known so far to be toxic to vultures.Over 10 years ago, the country banned the veterinary drug diclofenac. As per Ornithologists, this is a landmark step to save the small existing population of Asia’s globally threatened vultures."
    },
    {
      "id": 2,
      "question": "National Urban Digital Mission is launched by which ministry?",
      "options": [
        {
          "label": "A",
          "text": "Home Ministry"
        },
        {
          "label": "B",
          "text": "Finance Ministry"
        },
        {
          "label": "C",
          "text": "Housing and Urban Affairs Ministry"
        },
        {
          "label": "D",
          "text": "Transport Ministry"
        }
      ],
      "answer": {
        "label": "C",
        "text": "Housing and Urban Affairs Ministry"
      },
      "explanation": "The Union Ministry of Housing and Urban Affairs has launched the “National Urban Digital Mission”. The aim of the mission is to create a shared digital infrastructure for cities.The mission would create a citizen centric approach to urban governance and service delivery in cities by 2022, and across all towns by 2024."
    },
    {
      "id": 3,
      "question": "‘Alpine Plant species’, which are critically endangered have been discovered in which state?",
      "options": [
        {
          "label": "A",
          "text": "Assam"
        },
        {
          "label": "B",
          "text": "Sikkim"
        },
        {
          "label": "C",
          "text": "Arunachal Pradesh"
        },
        {
          "label": "D",
          "text": "Himachal Pradesh"
        }
      ],
      "answer": {
        "label": "C",
        "text": "Arunachal Pradesh"
      },
      "explanation": "A new species of the ‘alpine plant’ in Arunachal Pradesh’s Tawang district has been discovered by a team of scientists of three institutes.The new species, which was named as ‘Cremanthodium indicum’, belongs to the family of Himalayan sunflower. The species is endemic to Penga-Teng Tso Lake of Tawang district of the state."
    },
    {
      "id": 4,
      "question": "What is the outlay of the Production Linked Incentive (PLI) Scheme approved for the pharmaceuticals and IT hardware sector?",
      "options": [
        {
          "label": "A",
          "text": "Rs 15000 crore, Rs 7350 crore"
        },
        {
          "label": "B",
          "text": "Rs 12000 crore, Rs 5750 crore"
        },
        {
          "label": "C",
          "text": "Rs 10000 crore, Rs 2340 crore"
        },
        {
          "label": "D",
          "text": "Rs 8000 crore, Rs 1250 crore"
        }
      ],
      "answer": {
        "label": "A",
        "text": "Rs 15000 crore, Rs 7350 crore"
      },
      "explanation": "The Union Cabinet has recently approved the Production Linked Incentive (PLI) Scheme for the pharmaceuticals and IT hardware sectors.The PLI scheme for pharmaceuticals with an outlay of Rs 15000 crore, has a duration of nine years, till 2028-29. The Cabinet also approved the PLI Scheme for IT hardware such as laptops, tablets, all-in-one PCs and servers with an outlay of Rs 7350 crore."
    },
    {
      "id": 5,
      "question": "Who is the new Chairman of National Commission for Scheduled Castes (NCSC)?",
      "options": [
        {
          "label": "A",
          "text": "Vijay Sampla"
        },
        {
          "label": "B",
          "text": "Ajith Doval"
        },
        {
          "label": "C",
          "text": "Kumar Murmurae"
        },
        {
          "label": "D",
          "text": "Suneet Singh"
        }
      ],
      "answer": {
        "label": "A",
        "text": "Vijay Sampla"
      },
      "explanation": "Vijay Sampla, former Union Minster recently took charge as the chairman of the National Commission for Scheduled Castes (NCSC), after being appointed by the President of India.He served as the Union Minister of state for Social Justice and Empowerment from 2014 to 2019. Ram Shankar Katheria was earlier the head of NCSC."
    },
    {
      "id": 6,
      "question": "Ministry of Jal Shakti has selected how many sites under Phase 4 of the Swachh Iconic Places (SIP) initiative?",
      "options": [
        {
          "label": "A",
          "text": "4"
        },
        {
          "label": "B",
          "text": "8"
        },
        {
          "label": "C",
          "text": "12"
        },
        {
          "label": "D",
          "text": "16"
        }
      ],
      "answer": {
        "label": "C",
        "text": "12"
      },
      "explanation": "The Department of Drinking Water and Sanitation (DDWS), Ministry of Jal Shakti has announced that it has selected 12 iconic sites under Phase 4 of the Swachh Iconic Places (SIP) initiative.SIP is an initiative of Swachh Bharat Mission Grameen (SBM-G), which aims to improve the sanitation and cleanliness standards at and around the sites. Ministry of Jal Shakti coordinates with the Ministry of Housing and Urban Affairs, Ministry of Tourism, Ministry of Culture and the State/UT governments."
    },
    {
      "id": 7,
      "question": "Which state approved a law to give life imprisonment to food adulterators?",
      "options": [
        {
          "label": "A",
          "text": "Kerala"
        },
        {
          "label": "B",
          "text": "Tamil Nadu"
        },
        {
          "label": "C",
          "text": "Karnataka"
        },
        {
          "label": "D",
          "text": "Madhya Pradesh"
        }
      ],
      "answer": {
        "label": "D",
        "text": "Madhya Pradesh"
      },
      "explanation": "Madhya Pradesh approved a law to give life imprisonment to food adulterators, with the cabinet recently approving a Penal Law (Madhya Pradesh Amendment) Bill, 2021.In 2019, a massive rally was organised in the state against food adulteration, with the participation of several citizens of all age groups."
    },
    {
      "id": 8,
      "question": "The Indian Air Force (IAF) aerobatic display teams are to participate in which country’s commemorative Air show?",
      "options": [
        {
          "label": "A",
          "text": "Japan"
        },
        {
          "label": "B",
          "text": "Sri Lanka"
        },
        {
          "label": "C",
          "text": "Bangladesh"
        },
        {
          "label": "D",
          "text": "France"
        }
      ],
      "answer": {
        "label": "B",
        "text": "Sri Lanka"
      },
      "explanation": "The Indian Air Force (IAF) aerobatic display teams, Suryakiran and Sarang, along with Light Combat Aircraft Tejas, are set to participate in the three-day Air Show.The Air Show is a part of the 70th-anniversary celebrations of the Sri Lanka Air Force (SLAF). Earlier, the SKAT- Suryakiran Aerobatic team participated in the 50th anniversary of SLAF in 2001, in Sri Lanka."
    },
    {
      "id": 9,
      "question": "Deepak Kumar, who won the silver medal at the Strandja Memorial Tournament in Bulgaria, is associated with which sports?",
      "options": [
        {
          "label": "A",
          "text": "Weight Lifting"
        },
        {
          "label": "B",
          "text": "Boxing"
        },
        {
          "label": "C",
          "text": "Wrestling"
        },
        {
          "label": "D",
          "text": "Badminton"
        }
      ],
      "answer": {
        "label": "B",
        "text": "Boxing"
      },
      "explanation": "Indian boxer Deepak Kumar has won the silver medal at the 72nd Strandja Memorial Tournament, recently held in Sofia, Bulgaria.Deepak Kumar was a silver medal winner of the Asian Games, and a former India Open gold-medallist."
    },
    {
      "id": 10,
      "question": "“Sugamya Bharat App” is being launched as a part of which ministry?",
      "options": [
        {
          "label": "A",
          "text": "Ministry of Home Affairs"
        },
        {
          "label": "B",
          "text": "Ministry of Social Justice and Empowerment"
        },
        {
          "label": "C",
          "text": "Ministry of External Affairs"
        },
        {
          "label": "D",
          "text": "Ministry of Women and Child Development"
        }
      ],
      "answer": {
        "label": "B",
        "text": "Ministry of Social Justice and Empowerment"
      },
      "explanation": "The Union Ministry of Social justice and Empowerment has developed an app named “Sugamya Bharat App”. It has been developed by the Department of Empowerment of Persons with Disabilities (DEPwD), for enhancing accessibility.It is being launched along with a hand book named “Access – The Photo Digest”."
    }
  ]
}