{
  "metadata": {
    "source": "gktoday.in",
    "category_slug": "current-affairs-quiz-september-2024",
    "title": "Current Affairs Quiz - September, 2024",
    "page": 2,
    "total_pages": 5,
    "generated_at": "2026-05-02 05:49:10",
    "total_questions": 10,
    "scraped_at": "2026-05-02 12:09:15"
  },
  "questions": [
    {
      "id": 11,
      "question": "Konyaks, who were in the news recently, are the largest tribes of which state?",
      "options": [
        {
          "label": "A",
          "text": "Nagaland"
        },
        {
          "label": "B",
          "text": "Assam"
        },
        {
          "label": "C",
          "text": "Manipur"
        },
        {
          "label": "D",
          "text": "Odisha"
        }
      ],
      "answer": {
        "label": "A",
        "text": "Nagaland"
      },
      "explanation": "The Konyak Union has requested the Nagaland government to fix the boundary line error between Mon district in Nagaland and Charaideo district in Assam on Google Maps. The Konyaks live in Mon district, Nagaland, and parts of Arunachal Pradesh (Tirap and Changlang districts). The term ‘Konyak’ translates to “men with black hair,” and they are divided into two groups: “Thendu” (Tattooed Face) and “Thentho” (White Face). The Konyaks are of Mongoloid origin, with 95% following Christianity. They speak the Konyak language from the Sino-Tibetan family and celebrate festivals like Aolingmonyu, Aonyimo, and Laoun-ongmo. They excel in making firearms, handicrafts, and their society is patriarchal."
    },
    {
      "id": 12,
      "question": "SAMRIDH scheme, recently seen in the news, is a flagship programme of which ministry?",
      "options": [
        {
          "label": "A",
          "text": "Ministry of Electronics and Information Technology"
        },
        {
          "label": "B",
          "text": "Ministry of New and Renewable Energy"
        },
        {
          "label": "C",
          "text": "Ministry of Earth Sciences"
        },
        {
          "label": "D",
          "text": "Ministry of Science and Technology"
        }
      ],
      "answer": {
        "label": "A",
        "text": "Ministry of Electronics and Information Technology"
      },
      "explanation": "The Union Ministry of Electronics & IT launched the 2nd Cohort of the Startup Accelerators of MeitY for Product Innovation, Development and Growth (SAMRIDH) scheme. SAMRIDH, started in August 2021, is a flagship program of Ministry of Electronics and Information Technology under the National Policy on Software Products – 2019. The program supports 300 software startups with a ₹99 crore budget over 4 years. It helps existing and new accelerators select and scale potential IT-based startups. SAMRIDH provides startups with customer connections, investor connections, and international market access to boost growth. The initiative aims to accelerate innovation, development, and growth in the tech sector."
    },
    {
      "id": 13,
      "question": "What are “Globba tyrnaensis and Globba janakiae”, recently seen in news?",
      "options": [
        {
          "label": "A",
          "text": "New species of medicinal herbs"
        },
        {
          "label": "B",
          "text": "New species of plants from the ginger family"
        },
        {
          "label": "C",
          "text": "Rare species of cactus"
        },
        {
          "label": "D",
          "text": "Newly discovered species of frogs"
        }
      ],
      "answer": {
        "label": "B",
        "text": "New species of plants from the ginger family"
      },
      "explanation": "Two new ginger species, Globba tyrnaensis and Globba janakiae, were discovered in Meghalaya’s Double Decker Living Root Bridge area. These plants, called “dancing girls” for their flower movement, belong to the Globba genus of ornamental plants in the ginger family. Globba tyrnaensis was found in Tyrna village at 731 meters elevation and also near Thangkharang Park. It has orange flowers, large anthers, and produces bulbils for propagation. Globba janakiae, with fewer than 10 individuals, has unique heart-shaped labellum and is critically endangered. It honors botanist EK Janaki Ammal."
    },
    {
      "id": 14,
      "question": "Recently, which state government has raised the insurance limit on surrogacy policy for women up to Rs 10 lakh?",
      "options": [
        {
          "label": "A",
          "text": "Bihar"
        },
        {
          "label": "B",
          "text": "Madhya Pradesh"
        },
        {
          "label": "C",
          "text": "Uttar Pradesh"
        },
        {
          "label": "D",
          "text": "Rajasthan"
        }
      ],
      "answer": {
        "label": "B",
        "text": "Madhya Pradesh"
      },
      "explanation": "The Madhya Pradesh government has increased insurance coverage for surrogacy policies from Rs 2 lakh to Rs 10 lakh for women. There are 126 institutions registered under the State Assisted Reproductive Technology and Surrogacy Regulation Act 2021 in MP, including ART banks and clinics. Surrogacy involves a woman (surrogate) carrying and giving birth to a child for another person or couple (the intended parents)."
    },
    {
      "id": 15,
      "question": "Recently, Abdelmadjid Tebboune has been elected as the president of which country?",
      "options": [
        {
          "label": "A",
          "text": "Algeria"
        },
        {
          "label": "B",
          "text": "Australia"
        },
        {
          "label": "C",
          "text": "Iran"
        },
        {
          "label": "D",
          "text": "Vietnam"
        }
      ],
      "answer": {
        "label": "A",
        "text": "Algeria"
      },
      "explanation": "In the 2024 Algerian presidential election, 78-year-old President Abdelmadjid Tebboune was re-elected with a huge win. He secured 94.65% of the valid votes, as per Mohamed Charfi, head of the election authority. The election was held on 7 September 2024, with 5.6 million voters out of 25 million eligible participants. President Tebboune was re-elected for a second five-year term. He was first elected in 2019, but the opposition boycotted that election. Tebboune, seen as military-backed, defeated rivals Abdelaali Hassani Cherif and Youcef Aouchiche, who gained 3% and 2.1% of votes, respectively."
    },
    {
      "id": 16,
      "question": "Which country recently resolved a WTO trade dispute with India over sugar subsidies?",
      "options": [
        {
          "label": "A",
          "text": "Brazil"
        },
        {
          "label": "B",
          "text": "China"
        },
        {
          "label": "C",
          "text": "Australia"
        },
        {
          "label": "D",
          "text": "Malaysia"
        }
      ],
      "answer": {
        "label": "A",
        "text": "Brazil"
      },
      "explanation": "Brazil and India have settled a WTO trade dispute over sugar subsidies, reflecting their strategic partnership. This resolution is part of their wider collaboration, which includes working together on ethanol technology and addressing global sugar surplus issues. Their relationship encompasses strategic dialogues, trade forums, and other cooperative mechanisms, highlighting their joint efforts to manage global sugar trade challenges and price issues."
    },
    {
      "id": 17,
      "question": "Recently, who has made history by becoming the first Indian to be elected as the President of the Olympic Council of Asia (OCA)?",
      "options": [
        {
          "label": "A",
          "text": "Vikrant Sinha"
        },
        {
          "label": "B",
          "text": "Viswanathan Anand"
        },
        {
          "label": "C",
          "text": "Randhir Singh"
        },
        {
          "label": "D",
          "text": "Arjun Goel"
        }
      ],
      "answer": {
        "label": "C",
        "text": "Randhir Singh"
      },
      "explanation": "Randhir Singh, a key figure in Indian sports administration, has been elected as the first Indian president of the Olympic Council of Asia (OCA) at its 44th General Assembly. Singh, who has been associated with the OCA for over 33 years, achieves a historic milestone for Asian sports. His deep experience and background in sports are expected to drive initiatives to strengthen the OCA’s global role, including preparations for the upcoming Asian Games and other major events."
    },
    {
      "id": 18,
      "question": "Recently, where was the “2nd Asia-Pacific Ministerial Conference on Civil Aviation” held?",
      "options": [
        {
          "label": "A",
          "text": "Kathmandu"
        },
        {
          "label": "B",
          "text": "New Delhi"
        },
        {
          "label": "C",
          "text": "Beijing"
        },
        {
          "label": "D",
          "text": "Tokyo"
        }
      ],
      "answer": {
        "label": "B",
        "text": "New Delhi"
      },
      "explanation": "The 2nd Asia Pacific Ministerial Conference on Civil Aviation was held at Bharat Mandapam, New Delhi. It was co-hosted by the International Civil Aviation Organization (ICAO) and the Ministry of Civil Aviation, Government of India. The first conference took place in 2018 in Beijing, China. India had offered to host the second conference in 2020, but it was postponed due to the COVID-19 pandemic. This conference came at a time when India’s aviation industry was transforming. As the world’s third-largest domestic aviation market, India aimed to become a hub for MRO services, cargo, and regional aviation."
    },
    {
      "id": 19,
      "question": "Recently, who has been unanimously re-elected as the Chairperson of the Parliamentary Committee on Official Language?",
      "options": [
        {
          "label": "A",
          "text": "Dharmendra Pradhan"
        },
        {
          "label": "B",
          "text": "JP Nadda"
        },
        {
          "label": "C",
          "text": "Rajnath Singh"
        },
        {
          "label": "D",
          "text": "Amit Shah"
        }
      ],
      "answer": {
        "label": "D",
        "text": "Amit Shah"
      },
      "explanation": "Home Minister Amit Shah was unanimously re-elected as Chairperson of the Parliamentary Committee on Official Language. The government aims for all government systems to operate in Indian languages by 2047. The Department of Official Language is developing software to automatically translate all languages of the Eighth Schedule. A meeting was held in New Delhi to reconstitute the committee after the formation of the new government. Amit Shah previously served as the committee’s Chairperson from 2019 to 2024."
    },
    {
      "id": 20,
      "question": "Mukhyamantri Ladli Behna Yojana, recently seen in the news, was launched by which state?",
      "options": [
        {
          "label": "A",
          "text": "Madhya Pradesh"
        },
        {
          "label": "B",
          "text": "Uttarakhand"
        },
        {
          "label": "C",
          "text": "Haryana"
        },
        {
          "label": "D",
          "text": "Rajasthan"
        }
      ],
      "answer": {
        "label": "A",
        "text": "Madhya Pradesh"
      },
      "explanation": "Madhya Pradesh Chief Minister Mohan Yadav recently announced an additional benefit under the Ladli Behna Yojana. Launched on March 15, 2023, the scheme aims to enhance women’s economic independence, improve health and nutrition for women and their children, and boost their role in family decisions. Women aged 21 to 60 receive Rs 1250 per month under the scheme. The program is managed by the Department of Women and Child Development."
    }
  ]
}