{
  "metadata": {
    "source": "gktoday.in",
    "category_slug": "gujarati-current-affairs",
    "title": "Current Affairs in Gujarati [ગુજરાતી કરંટ અફેર્સ 2026-27]",
    "page": 1,
    "total_pages": 5,
    "generated_at": "2026-05-02 05:51:07",
    "total_questions": 10,
    "scraped_at": "2026-05-02 12:14:46"
  },
  "questions": [
    {
      "id": 1,
      "question": "તાજેતરમાં, કયા દેશે ગંભીર દુષ્કાળને કારણે 200 હાથીઓને મારવાની યોજના જાહેર કરી છે?",
      "options": [
        {
          "label": "A",
          "text": "વિયેતનામ"
        },
        {
          "label": "B",
          "text": "ઈન્ડોનેશિયા"
        },
        {
          "label": "C",
          "text": "ઝિમ્બાબ્વે"
        },
        {
          "label": "D",
          "text": "સિંગાપુર"
        }
      ],
      "answer": {
        "label": "C",
        "text": "ઝિમ્બાબ્વે"
      },
      "explanation": "ઝિમ્બાબ્વે 40 વર્ષમાં સૌથી ખરાબ દુષ્કાળને કારણે ગંભીર ભૂખમરાનો સામનો કરી રહેલા સમુદાયોને ખોરાક પૂરો પાડવા માટે 200 હાથીઓને મારવાની યોજના ધરાવે છે. એલ નિનો (El Niño) પ્રેરિત દુષ્કાળે દક્ષિણ આફ્રિકામાં 68 મિલિયન લોકોને અસર કરી, જેના પરિણામે વ્યાપક ખોરાકની અછત સર્જાઈ. 1988 બાદનું આ પ્રથમ હત્યાકાંડ હ્વાંગે, એમબીરે, ત્શોલોત્શો અને ચિરેડઝી જિલ્લાઓમાં થશે અને તે નામીબીયાના તાજેતરના 83 હાથીઓના કટોકટી પછીનું છે. આ કટોકટીનો હેતુ ખોરાક પૂરો પાડવાનો અને હાથીઓની વસ્તી ઘટાડવાનો છે, જે ઉદ્યાનની ક્ષમતા 55,000 કરતાં વધુ છે. ઝિમ્બાબ્વે પાસે 84,000 થી વધુ હાથીઓ છે અને તે તેના $600,000 મૂલ્યના સ્ટોકપાઈલ્સનું સંચાલન કરવા માટે હાથીદાંત (ivory)ના વેપારને ફરીથી ખોલવાની હિમાયત કરી રહ્યું છે."
    },
    {
      "id": 2,
      "question": "DESERT CYCLONE–II ભારત અને કયા દેશ વચ્ચેની સંયુક્ત સૈન્ય કસરત છે?",
      "options": [
        {
          "label": "A",
          "text": "યુનાઇટેડ અરબ અમીરાત (UAE)"
        },
        {
          "label": "B",
          "text": "ઇઝરાયલ"
        },
        {
          "label": "C",
          "text": "રશિયા"
        },
        {
          "label": "D",
          "text": "ફ્રાન્સ"
        }
      ],
      "answer": {
        "label": "A",
        "text": "યુનાઇટેડ અરબ અમીરાત (UAE)"
      },
      "explanation": "DESERT CYCLONE–II કસરત 18 થી 30 ડિસેમ્બર સુધી અબુ ધાબી ખાતે યોજાઈ હતી. આ ભારતીય સેના અને UAE લૅન્ડ ફોર્સ વચ્ચેની સંયુક્ત કસરત છે, જે રક્ષણ સહકાર અને પ્રદેશની સુરક્ષા મજબૂત બનાવે છે. કસરતમાં શહેરી ઓપરેશન, યુએન મંડેટ હેઠળના અભ્યાસ તથા સહકાર્યક્ષમતા વધારવા પર ભાર આપવામાં આવ્યો હતો."
    },
    {
      "id": 3,
      "question": "ઈલેક્ટ્રોનિક્સ ઘટકો ઉત્પાદન યોજના (ECMS) કઈ મંત્રાલયે શરૂ કરી હતી?",
      "options": [
        {
          "label": "A",
          "text": "વાણિજ્ય અને ઉદ્યોગ મંત્રાલય"
        },
        {
          "label": "B",
          "text": "માઇક્રો, લઘુ અને મધ્યમ ઉદ્યોગ મંત્રાલય"
        },
        {
          "label": "C",
          "text": "ભારી ઉદ્યોગ મંત્રાલય"
        },
        {
          "label": "D",
          "text": "ઈલેક્ટ્રોનિક્સ અને માહિતી પ્રૌદ્યોગિકી મંત્રાલય"
        }
      ],
      "answer": {
        "label": "D",
        "text": "ઈલેક્ટ્રોનિક્સ અને માહિતી પ્રૌદ્યોગિકી મંત્રાલય"
      },
      "explanation": "ઈલેક્ટ્રોનિક્સ અને માહિતી પ્રૌદ્યોગિકી મંત્રાલય (MeitY) દ્વારા ECMS શરૂ કરવામાં આવી હતી. આ યોજના હેઠળ 22 પ્રસ્તાવો મંજૂર થયા છે, જેમાં રૂ. 41,863 કરોડનું રોકાણ અને રૂ. 2,58,152 કરોડનું ઉત્પાદન થવાની શક્યતા છે. યોજનાનો ઉદ્દેશ દેશી ઉત્પાદનને પ્રોત્સાહન આપવા અને મજબૂત સપ્લાય ચેઇન વિકસાવવા છે."
    },
    {
      "id": 4,
      "question": "પ્રથમ વંદે ભારત સ્લીપર ટ્રેન કયા બે શહેરો વચ્ચે ચલાવવાની યોજના છે?",
      "options": [
        {
          "label": "A",
          "text": "દિલ્હી – મુંબઈ"
        },
        {
          "label": "B",
          "text": "ગૌહાટી – હાવડા"
        },
        {
          "label": "C",
          "text": "ચેન્નઈ – બેંગલુરુ"
        },
        {
          "label": "D",
          "text": "પટણા – કોલકાતા"
        }
      ],
      "answer": {
        "label": "B",
        "text": "ગૌહાટી – હાવડા"
      },
      "explanation": "ભારતીય રેલ્વે પોતાની પ્રથમ વંદે ભારત સ્લીપર ટ્રેન ગૌહાટી (આસામ) અને હાવડા (પશ્ચિમ બંગાળ) વચ્ચે શરૂ કરશે. ટ્રેનમાં 16 એસી કોચ હશે અને લગભગ 823 મુસાફરો માટે સુવિધા રહેશે. નવી સુવિધાઓ સાથે, આ સેવા રાત્રી પ્રવાસને વધુ આરામદાયક બનાવશે અને પ્રદેશીય જોડાણ વધારશે."
    },
    {
      "id": 5,
      "question": "RQ-170 “Sentinel” સ્ટેલ્થ સર્વેલન્સ ડ્રોન કયા દેશમાં વિકસાવવામાં આવ્યો છે?",
      "options": [
        {
          "label": "A",
          "text": "ચીન"
        },
        {
          "label": "B",
          "text": "જાપાન"
        },
        {
          "label": "C",
          "text": "રશિયા"
        },
        {
          "label": "D",
          "text": "યુનાઇટેડ સ્ટેટ્સ"
        }
      ],
      "answer": {
        "label": "D",
        "text": "યુનાઇટેડ સ્ટેટ્સ"
      },
      "explanation": "RQ-170 “Sentinel” સ્ટેલ્થ સર્વેલન્સ ડ્રોન યુનાઇટેડ સ્ટેટ્સ દ્વારા વિકસાવવામાં આવ્યો છે. આ ડ્રોન યુ.એસ. એર ફોર્સ માટે લોકહેડ માર્ટિનની સ્કંક વર્ક્સ ડિવિઝન દ્વારા ડિઝાઇન અને બનાવવામાં આવ્યો છે. તેનો ઉપયોગ ગુપ્તચર, સર્વેલન્સ અને રિકોનિસન્સ માટે થાય છે."
    },
    {
      "id": 6,
      "question": "ભારતમાં પહેલી વ્યાવસાયિક સ્તરની ઉષ્ણકટિબંધીય રિસર્ક્યુલેટિંગ એક્વાકલ્ચર સિસ્ટમ (RAS) આધારિત રેઇનબો ટ્રાઉટ એક્વાકલ્ચર ફાર્મ ક્યાં ઉદ્ઘાટન કરવામાં આવ્યું હતું?",
      "options": [
        {
          "label": "A",
          "text": "દેહરાદૂન, ઉત્તરાખંડ"
        },
        {
          "label": "B",
          "text": "લેહ, લદાખ"
        },
        {
          "label": "C",
          "text": "શિમલા, હિમાચલ પ્રદેશ"
        },
        {
          "label": "D",
          "text": "હૈદરાબાદ, તેલંગાણા"
        }
      ],
      "answer": {
        "label": "D",
        "text": "હૈદરાબાદ, તેલંગાણા"
      },
      "explanation": "Union મંત્રી શ્રી રાજીવ રંજન સિંહે 5 જાન્યુઆરી 2026ના રોજ હૈદરાબાદ, તેલંગાણામાં ભારતમાં પહેલી વ્યાવસાયિક સ્તરની ઉષ્ણકટિબંધીય RAS આધારિત રેઇનબો ટ્રાઉટ એક્વાકલ્ચર ફાર્મ અને સંશોધન સંસ્થાનું ઉદ્ઘાટન કર્યું. આ પ્રોજેક્ટ યુવાનોને આધુનિક એક્વાકલ્ચર, ઓટોમેશન અને બાયોસિક્યુરિટી અંગે પ્રાયોગિક તાલીમ આપે છે અને માછીમારી ક્ષેત્રની માનવ શક્તિ મજબૂત બનાવે છે."
    },
    {
      "id": 7,
      "question": "દુનિયામાં સૌપ્રથમ, કયા દેશમાં રોડ નિર્માણ માટે વ્યાવસાયિક રીતે બાયો-બિટુમિનનું ઉત્પાદન શરૂ થયું છે?",
      "options": [
        {
          "label": "A",
          "text": "બ્રાઝીલ"
        },
        {
          "label": "B",
          "text": "જર્મની"
        },
        {
          "label": "C",
          "text": "ભારત"
        },
        {
          "label": "D",
          "text": "ફ્રાંસ"
        }
      ],
      "answer": {
        "label": "C",
        "text": "ભારત"
      },
      "explanation": "ભારત એ દુનિયાનું પહેલું દેશ બન્યું છે, જેણે રોડ નિર્માણ માટે વ્યાવસાયિક રીતે બાયો-બિટુમિનનું ઉત્પાદન શરૂ કર્યું છે. આ પગલાથી ખેતીના અવશેષના દહનથી થતા પ્રદૂષણમાં ઘટાડો થશે અને વિકાસિત ભારત 2047ના વિઝનને ટેકો મળશે. આ પહેલ Waste to Wealth અને આત્મનિર્ભર ભારત મિશન સાથે સંકળાયેલી છે."
    },
    {
      "id": 8,
      "question": "તાજેતરમાં સમાચારમાં આવેલા ઇન્ડિયન જાયન્ટ સ્ક્વિરલ કયા રાજ્યનું રાજ્ય પ્રાણી છે?",
      "options": [
        {
          "label": "A",
          "text": "મધ્ય પ્રદેશ"
        },
        {
          "label": "B",
          "text": "કર્ણાટક"
        },
        {
          "label": "C",
          "text": "કેરળ"
        },
        {
          "label": "D",
          "text": "મહારાષ્ટ્ર"
        }
      ],
      "answer": {
        "label": "D",
        "text": "મહારાષ્ટ્ર"
      },
      "explanation": "2026ની ઓલ ઇન્ડિયા ટાઇગર એસ્ટિમેશન સર્વે દરમિયાન, પુણેના અટવન વિસ્તારમાં ઇન્ડિયન જાયન્ટ સ્ક્વિરલ જોવા મળ્યું હતું. તેને માલાબાર જાયન્ટ સ્ક્વિરલ અથવા સ્થાનિક ભાષામાં શેકરુ પણ કહે છે. આ વિશ્વની સૌથી મોટી સ્ક્વિરલ પ્રજાતિમાંની એક છે અને મુખ્યત્વે પશ્ચિમઘાટ, પૂર્વઘાટ અને સતપુડા પર્વતશ્રેણીમાં જોવા મળે છે. મહારાષ્ટ્રનું રાજ્ય પ્રાણી છે."
    },
    {
      "id": 9,
      "question": "ઓપરેશન પવન કઈ સંસ્થા દ્વારા ચલાવવામાં આવ્યું હતું?",
      "options": [
        {
          "label": "A",
          "text": "ઇન્ડિયન પીસકીપિંગ ફોર્સ (IPKF)"
        },
        {
          "label": "B",
          "text": "નેશનલ સિક્યુરિટી ગાર્ડ (NSG)"
        },
        {
          "label": "C",
          "text": "સેન્ટ્રલ બ્યુરો ઑફ ઇન્વેસ્ટિગેશન (CBI)"
        },
        {
          "label": "D",
          "text": "ઇન્ટેલિજન્સ બ્યુરો (IB)"
        }
      ],
      "answer": {
        "label": "A",
        "text": "ઇન્ડિયન પીસકીપિંગ ફોર્સ (IPKF)"
      },
      "explanation": "ઓપરેશન પવન 29 જુલાઈ 1987ના ઇન્ડો-શ્રીલંકા કરાર પછી ઇન્ડિયન પીસકીપિંગ ફોર્સ (IPKF) દ્વારા શ્રીલંકામાં હાથ ધરાયું હતું. આ દળ માર્ચ 1990 સુધી ત્યાં તૈનાત રહ્યું. ભારતીય જવાનોની બહાદુરી અને બલિદાનને સરકાર દ્વારા સન્માન આપવામાં આવ્યું છે."
    },
    {
      "id": 10,
      "question": "તાજેતરમાં સમાચારમાં આવેલી રૂટ વિલ્ટ રોગ કયા એજન્ટથી થાય છે?",
      "options": [
        {
          "label": "A",
          "text": "બેક્ટેરિયા"
        },
        {
          "label": "B",
          "text": "વાયરસ"
        },
        {
          "label": "C",
          "text": "ફૂગ"
        },
        {
          "label": "D",
          "text": "પ્રોટોઝોઆ"
        }
      ],
      "answer": {
        "label": "A",
        "text": "બેક્ટેરિયા"
      },
      "explanation": "તાજેતરમાં કર્ણાટક, તમિલનાડુ અને કેરળમાં પરંપરાગત નાળિયેર ક્ષેત્રોમાં ફાઇટોપ્લાઝ્મા બેક્ટેરિયા કારણે રૂટ વિલ્ટ રોગે ભારે નુકસાન કર્યું છે. આ રોગ પામના ઉત્પાદનને નોંધપાત્ર રીતે ઘટાડે છે, પણ પામના છોડને મારે નહીં. રોગ મુખ્યત્વે જીવાત, પવન અને સતત નાળિયેર વાવેતરથી ફેલાય છે."
    }
  ]
}