{
  "metadata": {
    "source": "gktoday.in",
    "category_slug": "current-affairs-quiz-january-2021",
    "title": "Current Affairs Quiz - January, 2021",
    "page": 4,
    "total_pages": 5,
    "generated_at": "2026-05-02 05:46:44",
    "total_questions": 10,
    "scraped_at": "2026-05-02 11:53:29"
  },
  "questions": [
    {
      "id": 31,
      "question": "Who is the Chairperson of the Start-up Advisory Council, constituted recently?",
      "options": [
        {
          "label": "A",
          "text": "NITI Aayog CEO"
        },
        {
          "label": "B",
          "text": "Prime Minister"
        },
        {
          "label": "C",
          "text": "Commerce and Industry Minister"
        },
        {
          "label": "D",
          "text": "ISRO Chairperson"
        }
      ],
      "answer": {
        "label": "C",
        "text": "Commerce and Industry Minister"
      },
      "explanation": "The Start-up Advisory Council was notified in January 2020, which aims to advise the Government to nurture innovation and start-ups in the country. It is chaired by the Commerce and Industry Minister.The Centre has recently nominated 28 non-official members for the Start-up Advisory Council notified last year, including the founders of top start-up firms in the country including Byju’s, Urban Company, Snapdeal and Ola Cabs."
    },
    {
      "id": 32,
      "question": "The Cabinet approved the MoU between India and which country in Solar Energy sector?",
      "options": [
        {
          "label": "A",
          "text": "France"
        },
        {
          "label": "B",
          "text": "Uzbekistan"
        },
        {
          "label": "C",
          "text": "Sri Lanka"
        },
        {
          "label": "D",
          "text": "Nepal"
        }
      ],
      "answer": {
        "label": "B",
        "text": "Uzbekistan"
      },
      "explanation": "The Union cabinet approved the signing of a memorandum of understanding (MoU) between India and Uzbekistan for solar energy cooperation.Under the MoU, the two countries will identify research and pilot projects in fields such as solar photovoltaic, storage technologies and technology transfer. National Institute of Solar Energy (NISE), Ministry of New & Renewable Energy is involved in the projects."
    },
    {
      "id": 33,
      "question": "Which country has decided to pause oil and gas leasing in Alaska’s Arctic National Wildlife Refuge?",
      "options": [
        {
          "label": "A",
          "text": "Canada"
        },
        {
          "label": "B",
          "text": "UK"
        },
        {
          "label": "C",
          "text": "USA"
        },
        {
          "label": "D",
          "text": "Ireland"
        }
      ],
      "answer": {
        "label": "C",
        "text": "USA"
      },
      "explanation": "The new US administration headed by Joe Biden has announced its plans to halt temporarily its oil and gas leasing in Alaska’s Arctic National Wildlife Refuge. The preceding administration headed by Trump had issued leases in this region which is considered sacred by Indigenous Gwich’in.Gwichʼin are an Athabaskan language speaking people of Canada and Alaska. They live in the northwestern part of North America close to the Arctic circle."
    },
    {
      "id": 34,
      "question": "The Reserve Bank of India (RBI) proposed a four-tier regulatory framework for which type of financial institutions?",
      "options": [
        {
          "label": "A",
          "text": "Payment Banks"
        },
        {
          "label": "B",
          "text": "NBFCs"
        },
        {
          "label": "C",
          "text": "Small Finance Banks"
        },
        {
          "label": "D",
          "text": "Foreign Banks"
        }
      ],
      "answer": {
        "label": "B",
        "text": "NBFCs"
      },
      "explanation": "Reserve Bank of India recently released a discussion paper on revised regulatory framework for Non-Banking Financial Companies (NBFCs).As per the paper, the regulatory and supervisory framework of NBFCs shall be based on a four-layered structure namely Base Layer, Middle Layer, Upper Layer and a possible Top Layer. RBI also recommended more power for the NBFC Boards on capital and risk management."
    },
    {
      "id": 35,
      "question": "‘Ooceraea joshii’, is an Ant species recently discovered in which state?",
      "options": [
        {
          "label": "A",
          "text": "Telangana"
        },
        {
          "label": "B",
          "text": "Kerala"
        },
        {
          "label": "C",
          "text": "Andhra Pradesh"
        },
        {
          "label": "D",
          "text": "Karnataka"
        }
      ],
      "answer": {
        "label": "B",
        "text": "Kerala"
      },
      "explanation": "Two new species of a rare ant genus have been recently discovered in Kerala and Tamil Nadu by a team of scientists from Punjabi University.One of the two species which was discovered found in the Periyar Tiger Reserve of Kerala has been named Ooceraea Joshii, to honour the veteran biologist ‘Amitabh Joshi’."
    },
    {
      "id": 36,
      "question": "“Operation Sard Hawa”, which was making news recently, was organised by which organisation?",
      "options": [
        {
          "label": "A",
          "text": "DRDO"
        },
        {
          "label": "B",
          "text": "ISRO"
        },
        {
          "label": "C",
          "text": "BSF"
        },
        {
          "label": "D",
          "text": "ITBP"
        }
      ],
      "answer": {
        "label": "C",
        "text": "BSF"
      },
      "explanation": "Border Security Force (BSF) organises the Operation “Garam Hawa” in summer season and operation “Sard Hawa” during the winter season every year.BSF has recently launched “Operation Sard Hawa” of this year, under which it aims to increase security on the borders in Jaisalmer, Rajasthan. This operation was scheduled from January 21 to 27, coinciding with the Republic Day."
    },
    {
      "id": 37,
      "question": "Which country proposed a five-year extension of New START Treaty with Russia?",
      "options": [
        {
          "label": "A",
          "text": "United States"
        },
        {
          "label": "B",
          "text": "United Kingdom"
        },
        {
          "label": "C",
          "text": "China"
        },
        {
          "label": "D",
          "text": "Japan"
        }
      ],
      "answer": {
        "label": "A",
        "text": "United States"
      },
      "explanation": "US President Joe Biden has recently proposed a five-year extension of New START Treaty with Russia.The treaty limited the United States and Russia to 1,550 nuclear warheads each. It expires on February 5 this year since the former President Donald Trump stopped negotiations and tried to include China in the treaty."
    },
    {
      "id": 38,
      "question": "Which Ministry has launched a National Migration Support Portal named “ShramShakti”?",
      "options": [
        {
          "label": "A",
          "text": "Union Labour Ministry"
        },
        {
          "label": "B",
          "text": "Union Home Ministry"
        },
        {
          "label": "C",
          "text": "Union Ministry of women and child welfare"
        },
        {
          "label": "D",
          "text": "Union Tribal Affairs Ministry"
        }
      ],
      "answer": {
        "label": "D",
        "text": "Union Tribal Affairs Ministry"
      },
      "explanation": "The Union Ministry of Tribal Affairs has launched a dedicated portal that would help in formulation of state and national-level programme for migrant workers. The portal is named ‘ShramShakti’ and was launched by the Union Tribal Affairs Minister at Goa. He also launched a training manual for the migrant workers named ShramSaathi."
    },
    {
      "id": 39,
      "question": "Which organization has issued Purple Notice to member countries against investment frauds via dating applications?",
      "options": [
        {
          "label": "A",
          "text": "UNFCCC"
        },
        {
          "label": "B",
          "text": "International Court of Justice"
        },
        {
          "label": "C",
          "text": "World Trade Organization"
        },
        {
          "label": "D",
          "text": "Interpol"
        }
      ],
      "answer": {
        "label": "D",
        "text": "Interpol"
      },
      "explanation": "The Interpol has issued “Purple Notice” to all its member countries. The notice warns all the member countries against investment frauds via dating applications.It has been stated that artificial romance is established with users of the apps in the initial stages and once a certain level of trust is achieved, criminals encourage users to join ponzi investment schemes."
    },
    {
      "id": 40,
      "question": "‘Udyam Sarathi’ and ‘Abhyudaya’ are the initiatives of which Indian state/UT?",
      "options": [
        {
          "label": "A",
          "text": "Gujarat"
        },
        {
          "label": "B",
          "text": "Maharashtra"
        },
        {
          "label": "C",
          "text": "Madhya Pradesh"
        },
        {
          "label": "D",
          "text": "Uttar Pradesh"
        }
      ],
      "answer": {
        "label": "D",
        "text": "Uttar Pradesh"
      },
      "explanation": "The Chief Minister of Uttar Pradesh has recently launched a mobile app named ‘Udyam Sarathi’ for seeking employment, as a part of the 3-day event marking UP DIWAS.The state also announced the proposal to launch ‘Abhyudaya’ coaching centres, which would benefit the students who are preparing for various competitive examinations."
    }
  ]
}