{
  "metadata": {
    "source": "gktoday.in",
    "category_slug": "uttar-pradesh-gk-questions-for-uppsc-examinations",
    "title": "States PCS: Uttar Pradesh GK Questions for UPPSC Examinations",
    "page": 4,
    "total_pages": 5,
    "generated_at": "2026-05-02 07:04:56",
    "total_questions": 10,
    "scraped_at": "2026-05-02 12:35:06"
  },
  "questions": [
    {
      "id": 31,
      "question": "Who ruled Mathura as Great Satrap around 10 CE?",
      "options": [
        {
          "label": "A",
          "text": "Menander I"
        },
        {
          "label": "B",
          "text": "Sodasa"
        },
        {
          "label": "C",
          "text": "Rajuvula"
        },
        {
          "label": "D",
          "text": "Strato II"
        }
      ],
      "answer": {
        "label": "C",
        "text": "Rajuvula"
      },
      "explanation": "Rajuvula was the Indo-Scythian Great Satrap of Mathura around 10 CE, succeeding Indo-Greek rule. He was succeeded by his son Sodasa. His inscriptions are an important source for early Kushan period history."
    },
    {
      "id": 32,
      "question": "Who led Nagari Pracharini Sabha to promote Hindi and Devanagari script in Uttar Pradesh?",
      "options": [
        {
          "label": "A",
          "text": "Munshi Premchand"
        },
        {
          "label": "B",
          "text": "Jaishankar Prasad"
        },
        {
          "label": "C",
          "text": "Pandit Madan Mohan Malaviya"
        },
        {
          "label": "D",
          "text": "Bhagat Singh"
        }
      ],
      "answer": {
        "label": "C",
        "text": "Pandit Madan Mohan Malaviya"
      },
      "explanation": "Pandit Madan Mohan Malaviya led Nagari Pracharini Sabha, promoted Hindi and Devanagari script, pushed Hindi’s use in education and courts, and launched the influential journal Saraswati in Uttar Pradesh, significantly influencing the Hindi movement."
    },
    {
      "id": 33,
      "question": "Who was the famous tawaif and ruler of Sardhana in Uttar Pradesh?",
      "options": [
        {
          "label": "A",
          "text": "Begum Hazrat Mahal"
        },
        {
          "label": "B",
          "text": "Begum Rokeya"
        },
        {
          "label": "C",
          "text": "Wazeeran"
        },
        {
          "label": "D",
          "text": "Begum Samru"
        }
      ],
      "answer": {
        "label": "D",
        "text": "Begum Samru"
      },
      "explanation": "Begum Samru, originally a tawaif, became the ruler of Sardhana near Meerut, Uttar Pradesh. She commanded a mercenary army and was influential in Indo-European politics during the late 18th and early 19th centuries. Her palace at Sardhana is now a historical church. She converted to Catholicism."
    },
    {
      "id": 34,
      "question": "Which Vaishnav Bairagi sect, founded by Ramananda, was allotted one-third of the disputed land in the Ayodhya case by the Allahabad High Court in 2010?",
      "options": [
        {
          "label": "A",
          "text": "Nirmohi Akhara"
        },
        {
          "label": "B",
          "text": "Dashanami Sampradaya"
        },
        {
          "label": "C",
          "text": "Udasin Sect"
        },
        {
          "label": "D",
          "text": "Ramanandi Sampradaya"
        }
      ],
      "answer": {
        "label": "A",
        "text": "Nirmohi Akhara"
      },
      "explanation": "Nirmohi Akhara, founded by Ramananda, claimed ancient worship rights and was allotted one-third of the Ayodhya disputed land by the Allahabad High Court in 2010."
    },
    {
      "id": 35,
      "question": "Which city serves as the starting point of the Eastern Dedicated Freight Corridor within the ADKIC industrial corridor?",
      "options": [
        {
          "label": "A",
          "text": "Allahabad"
        },
        {
          "label": "B",
          "text": "Kanpur"
        },
        {
          "label": "C",
          "text": "Lucknow"
        },
        {
          "label": "D",
          "text": "Varanasi"
        }
      ],
      "answer": {
        "label": "A",
        "text": "Allahabad"
      },
      "explanation": "The Eastern Dedicated Freight Corridor begins at Allahabad, a key city in the ADKIC spanning seven states in Uttar Pradesh."
    },
    {
      "id": 36,
      "question": "Who was the businessman implicated in the 2006 Noida serial murders case in Uttar Pradesh?",
      "options": [
        {
          "label": "A",
          "text": "Surinder Koli"
        },
        {
          "label": "B",
          "text": "Moninder Singh Pandher"
        },
        {
          "label": "C",
          "text": "Vikas Yadav"
        },
        {
          "label": "D",
          "text": "Rajesh Kumar"
        }
      ],
      "answer": {
        "label": "B",
        "text": "Moninder Singh Pandher"
      },
      "explanation": "Moninder Singh Pandher, a businessman from Noida, was involved along with servant Surinder Koli in the 2006 serial murders case."
    },
    {
      "id": 37,
      "question": "Consider the following pairs regarding medieval rulers and their corresponding contributions to Uttar Pradesh: Akbar – Built Fatehpur Sikri as capital Sikandar Lodi – Founded the city of Agra Ibrahim Sharqi – Commissioned Atala Masjid Aurangzeb – Reimposed Jizya on non-Muslims Which of the above pairs are correctly matched?",
      "options": [
        {
          "label": "A",
          "text": "Only 1 and 2"
        },
        {
          "label": "B",
          "text": "1, 2 and 3"
        },
        {
          "label": "C",
          "text": "2, 3 and 4"
        },
        {
          "label": "D",
          "text": "All are correctly matched"
        }
      ],
      "answer": {
        "label": "D",
        "text": "All are correctly matched"
      },
      "explanation": "All four pairs are correctly matched: Akbar established Fatehpur Sikri as his capital in the 16th century. Sikandar Lodi founded Agra in the late 15th century. Ibrahim Sharqi commissioned the Atala Masjid in Jaunpur. Aurangzeb infamously reimposed the Jizya tax on non-Muslims in his reign. These events are well-documented aspects of the medieval history of Uttar Pradesh."
    },
    {
      "id": 38,
      "question": "What are the approximate east–west length and north–south breadth of Uttar Pradesh, respectively?",
      "options": [
        {
          "label": "A",
          "text": "650 km (length), 240 km (breadth)"
        },
        {
          "label": "B",
          "text": "350 km (length), 160 km (breadth)"
        },
        {
          "label": "C",
          "text": "800 km (length), 320 km (breadth)"
        },
        {
          "label": "D",
          "text": "425 km (length), 210 km (breadth)"
        }
      ],
      "answer": {
        "label": "A",
        "text": "650 km (length), 240 km (breadth)"
      },
      "explanation": "The east–west length of Uttar Pradesh is about 650 km, and its north–south breadth is about 240 km."
    },
    {
      "id": 39,
      "question": "In Uttar Pradesh, which soil type, due to its high pH and sodium content, cannot be rejuvenated naturally without artificial nutrient supplementation and shows poor response to organic manuring?",
      "options": [
        {
          "label": "A",
          "text": "Terai soil"
        },
        {
          "label": "B",
          "text": "Bhabar soil"
        },
        {
          "label": "C",
          "text": "Usar soil"
        },
        {
          "label": "D",
          "text": "Alluvial soil"
        }
      ],
      "answer": {
        "label": "C",
        "text": "Usar soil"
      },
      "explanation": "Usar soil in Uttar Pradesh is saline-alkaline with high sodium and pH; it cannot recover without artificial supplements like gypsum and reacts poorly to organic manure."
    },
    {
      "id": 40,
      "question": "Match the following Bird Sanctuaries with their respective locations: Bakhira Bird Sanctuary Okhla Bird Sanctuary Patna Bird Sanctuary Parvati Aranga Bird Sanctuary Sanctuary locations: Sant Kabir Nagar Gautam Buddh Nagar Etah Gonda Which of the following pairs is/are correctly matched?",
      "options": [
        {
          "label": "A",
          "text": "A-4, B-2, C-3, D-1"
        },
        {
          "label": "B",
          "text": "A-1, B-2, C-3, D-4"
        },
        {
          "label": "C",
          "text": "A-2, B-1, C-4, D-3"
        },
        {
          "label": "D",
          "text": "A-1, B-3, C-2, D-4"
        }
      ],
      "answer": {
        "label": "B",
        "text": "A-1, B-2, C-3, D-4"
      },
      "explanation": "Bakhira Bird Sanctuary is in Sant Kabir Nagar district, Okhla Bird Sanctuary in Gautam Buddh Nagar (Noida), Patna Bird Sanctuary in Etah, and Parvati Aranga Bird Sanctuary in Gonda. The correct order is A-1, B-2, C-3, D-4. Each sanctuary is an important conservation site known for rich avifaunal diversity and wetland ecosystems."
    }
  ]
}